emopoint/__init__.py
emopoint/generated.py
emopoint/lib.py
emopoint/tests/test_lib.py
emopoint-0.1.3.dist-info/LICENSE
emopoint-0.1.3.dist-info/METADATA
emopoint-0.1.3.dist-info/WHEEL
emopoint-0.1.3.dist-info/RECORD
