Metadata-Version: 2.1
Name: emopoint
Version: 0.1.3
Summary: A library for mapping text into a multidimensional embedding space representing emotion
License: Apache 2
Author: Tim Kellogg
Author-email: timothy.kellogg@gmail.com
Requires-Python: >=3.8,<4.0
Classifier: License :: Other/Proprietary License
Classifier: Programming Language :: Python :: 3
Classifier: Programming Language :: Python :: 3.8
Classifier: Programming Language :: Python :: 3.9
Classifier: Programming Language :: Python :: 3.10
Classifier: Programming Language :: Python :: 3.11
Requires-Dist: numpy (>=1.0)
